cmsplugin_feed_ai/__init__.py
cmsplugin_feed_ai/cms_plugins.py
cmsplugin_feed_ai/feed.py
cmsplugin_feed_ai/models.py
cmsplugin_feed_ai/utils.py
cmsplugin_feed_ai/management/__init__.py
cmsplugin_feed_ai/management/commands/__init__.py
cmsplugin_feed_ai/management/commands/test_social_feeds.py
cmsplugin_feed_ai/migrations/0001_initial.py
cmsplugin_feed_ai/migrations/__init__.py
cmsplugin_feed_ai/providers/__init__.py
cmsplugin_feed_ai/providers/common.py
cmsplugin_feed_ai/providers/exceptions.py
cmsplugin_feed_ai/providers/facebook.py
cmsplugin_feed_ai/providers/twitter.py
cmsplugin_feed_ai/templates/cmsplugin_feed_ai/feed.html
cmsplugin_feed_ai-0.0.1.dist-info/DESCRIPTION.rst
cmsplugin_feed_ai-0.0.1.dist-info/METADATA
cmsplugin_feed_ai-0.0.1.dist-info/RECORD
cmsplugin_feed_ai-0.0.1.dist-info/WHEEL
cmsplugin_feed_ai-0.0.1.dist-info/metadata.json
cmsplugin_feed_ai-0.0.1.dist-info/top_level.txt
